movslib/__init__.py
movslib/_java.py
movslib/autotag/__init__.py
movslib/autotag/autotag.py
movslib/autotag/model.py
movslib/buoni.py
movslib/estrattoconto/__init__.py
movslib/estrattoconto/template_1.json
movslib/estrattoconto/template_2.json
movslib/estrattoconto/template_3.json
movslib/iterhelper.py
movslib/libretto.py
movslib/listamovimentixlsx.py
movslib/model.py
movslib/movs.py
movslib/postepay.py
movslib/py.typed
movslib/reader.py
movslib/scansioni.py
zeed_movslib-0.0.13.dist-info/METADATA
zeed_movslib-0.0.13.dist-info/WHEEL
zeed_movslib-0.0.13.dist-info/entry_points.txt
zeed_movslib-0.0.13.dist-info/licenses/LICENSE
zeed_movslib-0.0.13.dist-info/RECORD
