Metadata-Version: 2.1
Name: zeed-movslib
Version: 0.0.13
License:                     GNU AFFERO GENERAL PUBLIC LICENSE
Classifier: Programming Language :: Python :: 3 :: Only
Classifier: Programming Language :: Python :: 3.12
Classifier: Programming Language :: Python :: 3.13
Project-URL: Homepage, https://github.com/ZeeD/movslib
Project-URL: Repository, https://github.com/ZeeD/movslib.git
Requires-Python: <3.14,>=3.12
Requires-Dist: jdk4py>=21.0.4.1
Requires-Dist: openpyxl>=3.1.5
Requires-Dist: pypdf>=4.2
Requires-Dist: tabula-py[jpype]>=2.9.3
